aioinstagrapi/__init__.py
aioinstagrapi/config.py
aioinstagrapi/exceptions.py
aioinstagrapi/extractors.py
aioinstagrapi/models.py
aioinstagrapi/utils.py
aioinstagrapi/mixins/account.py
aioinstagrapi/mixins/album.py
aioinstagrapi/mixins/bloks.py
aioinstagrapi/mixins/challenge.py
aioinstagrapi/mixins/clip.py
aioinstagrapi/mixins/collection.py
aioinstagrapi/mixins/comment.py
aioinstagrapi/mixins/direct.py
aioinstagrapi/mixins/explore.py
aioinstagrapi/mixins/fbsearch.py
aioinstagrapi/mixins/fundraiser.py
aioinstagrapi/mixins/hashtag.py
aioinstagrapi/mixins/helpers.py
aioinstagrapi/mixins/highlight.py
aioinstagrapi/mixins/igtv.py
aioinstagrapi/mixins/insights.py
aioinstagrapi/mixins/location.py
aioinstagrapi/mixins/media.py
aioinstagrapi/mixins/multiple_accounts.py
aioinstagrapi/mixins/note.py
aioinstagrapi/mixins/notification.py
aioinstagrapi/mixins/password.py
aioinstagrapi/mixins/photo.py
aioinstagrapi/mixins/private.py
aioinstagrapi/mixins/public.py
aioinstagrapi/mixins/setters.py
aioinstagrapi/mixins/share.py
aioinstagrapi/mixins/story.py
aioinstagrapi/mixins/timeline.py
aioinstagrapi/mixins/totp.py
aioinstagrapi/mixins/track.py
aioinstagrapi/mixins/user.py
aioinstagrapi/mixins/video.py
aioinstagrapi/mixins/__pycache__/account.cpython-38.pyc
aioinstagrapi/mixins/__pycache__/album.cpython-38.pyc
aioinstagrapi/mixins/__pycache__/bloks.cpython-38.pyc
aioinstagrapi/mixins/__pycache__/challenge.cpython-38.pyc
aioinstagrapi/mixins/__pycache__/clip.cpython-38.pyc
aioinstagrapi/mixins/__pycache__/collection.cpython-38.pyc
aioinstagrapi/mixins/__pycache__/comment.cpython-38.pyc
aioinstagrapi/mixins/__pycache__/direct.cpython-38.pyc
aioinstagrapi/mixins/__pycache__/explore.cpython-38.pyc
aioinstagrapi/mixins/__pycache__/fbsearch.cpython-38.pyc
aioinstagrapi/mixins/__pycache__/fundraiser.cpython-38.pyc
aioinstagrapi/mixins/__pycache__/hashtag.cpython-38.pyc
aioinstagrapi/mixins/__pycache__/helpers.cpython-38.pyc
aioinstagrapi/mixins/__pycache__/highlight.cpython-38.pyc
aioinstagrapi-1.1.21.dist-info/LICENSE.txt
aioinstagrapi-1.1.21.dist-info/METADATA
aioinstagrapi-1.1.21.dist-info/WHEEL
aioinstagrapi-1.1.21.dist-info/top_level.txt
aioinstagrapi-1.1.21.dist-info/RECORD
